zope.server-5.0-py3.11-nspkg.pth
zope/server/__init__.py
zope/server/adjustments.py
zope/server/buffers.py
zope/server/dualmodechannel.py
zope/server/fixedstreamreceiver.py
zope/server/maxsockets.py
zope/server/serverbase.py
zope/server/serverchannelbase.py
zope/server/task.py
zope/server/taskthreads.py
zope/server/trigger.py
zope/server/utilities.py
zope/server/zlogintegration.py
zope/server/ftp/README.rst
zope/server/ftp/__init__.py
zope/server/ftp/logger.py
zope/server/ftp/publisher.py
zope/server/ftp/server.py
zope/server/ftp/tests/__init__.py
zope/server/ftp/tests/demofs.py
zope/server/ftp/tests/fstests.py
zope/server/ftp/tests/test_demofs.py
zope/server/ftp/tests/test_ftpserver.py
zope/server/ftp/tests/test_logger.py
zope/server/ftp/tests/test_publisher.py
zope/server/http/__init__.py
zope/server/http/chunking.py
zope/server/http/commonaccesslogger.py
zope/server/http/http_date.py
zope/server/http/httprequestparser.py
zope/server/http/httpserver.py
zope/server/http/httpserverchannel.py
zope/server/http/httptask.py
zope/server/http/publisherhttpserver.py
zope/server/http/wsgihttpserver.py
zope/server/http/tests/__init__.py
zope/server/http/tests/test_chunking.py
zope/server/http/tests/test_commonaccesslogger.py
zope/server/http/tests/test_httpdate.py
zope/server/http/tests/test_httprequestparser.py
zope/server/http/tests/test_httpserver.py
zope/server/http/tests/test_httptask.py
zope/server/http/tests/test_publisherhttpserver.py
zope/server/http/tests/test_wsgiserver.py
zope/server/interfaces/__init__.py
zope/server/interfaces/ftp.py
zope/server/interfaces/logger.py
zope/server/linereceiver/__init__.py
zope/server/linereceiver/linecommandparser.py
zope/server/linereceiver/lineserverchannel.py
zope/server/linereceiver/linetask.py
zope/server/linereceiver/tests/__init__.py
zope/server/linereceiver/tests/test_linecommandparser.py
zope/server/linereceiver/tests/test_lineserverchannel.py
zope/server/logger/__init__.py
zope/server/logger/pythonlogger.py
zope.server-5.0.dist-info/LICENSE.txt
zope.server-5.0.dist-info/METADATA
zope.server-5.0.dist-info/WHEEL
zope.server-5.0.dist-info/entry_points.txt
zope.server-5.0.dist-info/namespace_packages.txt
zope.server-5.0.dist-info/top_level.txt
zope.server-5.0.dist-info/RECORD
